segrs/RSmerge.py
segrs/RSsplit.py
segrs/__init__.py
segrs-0.1.3.dist-info/METADATA
segrs-0.1.3.dist-info/WHEEL
segrs-0.1.3.dist-info/top_level.txt
segrs-0.1.3.dist-info/RECORD
