Metadata-Version: 2.1
Name: segrs
Version: 0.1.3
Summary: Remote Sensing Image Segmentation Tools
Author: zhibo wang
Author-email: 
Keywords: python,segrs,Remote Sensing,Segmentation
Classifier: Development Status :: 1 - Planning
Classifier: Intended Audience :: Developers
Classifier: Programming Language :: Python :: 3
Classifier: Operating System :: Unix
Classifier: Operating System :: MacOS :: MacOS X
Classifier: Operating System :: Microsoft :: Windows
